mcp/__init__.py
mcp/run_server.py
mcp/server.py
mcp/start_mcp.py
mcp/tools.py
mseep_crewai-0.1.2.dist-info/METADATA
mseep_crewai-0.1.2.dist-info/WHEEL
mseep_crewai-0.1.2.dist-info/entry_points.txt
mseep_crewai-0.1.2.dist-info/top_level.txt
mseep_crewai-0.1.2.dist-info/RECORD
