Metadata-Version: 2.4
Name: mseep-crewai
Version: 0.1.2
Summary: crewai using crewAI
Home-page: 
Author: mseep
Author-email: mseep <support@skydeck.ai>
Maintainer-email: mseep <support@skydeck.ai>
Requires-Python: >=3.6
Requires-Dist: crewai[tools]<1.0.0,>=0.114.0
Requires-Dist: fastapi>=0.95.0
Requires-Dist: uvicorn>=0.22.0
Requires-Dist: pydantic>=2.0.0
Dynamic: author
Dynamic: requires-python
